agi_open_network_cn/__init__.py
agi_open_network_cn/exceptions.py
siliconflow_framework/__init__.py
siliconflow_framework/client.py
siliconflow_framework/models.py
agi_open_network_cn-0.1.0.dist-info/LICENSE
agi_open_network_cn-0.1.0.dist-info/METADATA
agi_open_network_cn-0.1.0.dist-info/WHEEL
agi_open_network_cn-0.1.0.dist-info/top_level.txt
agi_open_network_cn-0.1.0.dist-info/RECORD
