Metadata-Version: 2.2
Name: agi-open-network-cn
Version: 0.1.0
Summary: AGI Open Network China Models - A Simple and Powerful Framework for Chinese AI Models
Home-page: https://github.com/agiopennetwork/agi-open-network-cn
Author: AGI Open Network Team
Author-email: AGI Open Network Team <info@agiopen.network>
License: MIT License
Project-URL: Homepage, https://www.agiopen.network
Project-URL: Repository, https://github.com/agiopennetwork/agi-open-network-cn
Keywords: agi,ai,machine learning,deep learning,nlp,computer vision,speech,chinese models
Classifier: Development Status :: 4 - Beta
Classifier: Intended Audience :: Developers
Classifier: License :: OSI Approved :: MIT License
Classifier: Operating System :: OS Independent
Classifier: Programming Language :: Python :: 3
Classifier: Programming Language :: Python :: 3.7
Classifier: Programming Language :: Python :: 3.8
Classifier: Programming Language :: Python :: 3.9
Classifier: Programming Language :: Python :: 3.10
Classifier: Topic :: Software Development :: Libraries :: Python Modules
Classifier: Topic :: Scientific/Engineering :: Artificial Intelligence
Requires-Python: >=3.7
License-File: LICENSE
Requires-Dist: requests>=2.25.0
Requires-Dist: tqdm>=4.65.0
Requires-Dist: pydantic>=2.0.0
Dynamic: author
Dynamic: home-page
Dynamic: requires-python
